README.md
extract_versions.py
setup.py
lockfile_extract.egg-info/PKG-INFO
lockfile_extract.egg-info/SOURCES.txt
lockfile_extract.egg-info/dependency_links.txt
lockfile_extract.egg-info/entry_points.txt
lockfile_extract.egg-info/top_level.txt