Metadata-Version: 2.1
Name: lockfile-extract
Version: 1.0.3
Summary: Extract package versions from package-lock.json without installing dependencies!
Home-page: https://github.com/sidhanshamil/lockfile-extract
Author: Sidhan Shamil M
Author-email: sidhanshamil3@gmail.com
License: MIT
Platform: UNKNOWN
Classifier: Programming Language :: Python :: 3
Classifier: License :: OSI Approved :: MIT License
Classifier: Operating System :: OS Independent
Requires-Python: >=3.6
